Metadata-Version: 2.1
Name: fiberorient
Version: 0.1
Summary: Tools for 3D structure tensor analysis
Home-page: https://github.com/scott-trinkle/fiberorient
Author: Scott Trinkle
Author-email: tscott.trinkle@gmail.com
License: MIT
Download-URL: https://github.com/scott-trinkle/fiberorient/archive/refs/tags/v_01.tar.gz
Keywords: structure tensor,orientation,ODF
Platform: UNKNOWN
Classifier: Development Status :: 3 - Alpha
Classifier: Intended Audience :: Developers
Classifier: Topic :: Software Development :: Build Tools
Classifier: License :: OSI Approved :: MIT License
Classifier: Programming Language :: Python :: 3.6
Classifier: Programming Language :: Python :: 3.7
Classifier: Programming Language :: Python :: 3.8
Classifier: Programming Language :: Python :: 3.9
